sistema_bancario/__init__.py
sistema_bancario/banco/__init__.py
sistema_bancario/banco/banco.py
sistema_bancario/banco/teste.py
sistema_bancario87/__init__.py
sistema_bancario87/banco/__init__.py
sistema_bancario87/banco/banco.py
sistema_bancario87/banco/teste.py
sistema_bancario87-0.0.1.dist-info/METADATA
sistema_bancario87-0.0.1.dist-info/WHEEL
sistema_bancario87-0.0.1.dist-info/top_level.txt
sistema_bancario87-0.0.1.dist-info/RECORD
