Metadata-Version: 2.1
Name: sistema-bancario87
Version: 0.0.1
Summary: Um projeto de teste para validar os meus conhecimentos adequeridos na plataforma da DIO
Home-page: https://github.com/Matthew8717
Author: Matthew
Author-email: 87sans878798@gmail.com
Requires-Python: >=3.9
